[
  {
    "instrumentName": "Whistle",
    "notes": [
      {
        "time": 0,
        "name": "C5",
        "velocity": 81,
        "duration": 700
      },
      {
        "time": 700,
        "name": "D5",
        "velocity": 81,
        "duration": 700
      },
      {
        "time": 1400,
        "name": "E5",
        "velocity": 81,
        "duration": 700
      },
      {
        "time": 2100,
        "name": "F5",
        "velocity": 81,
        "duration": 700
      },
      {
        "time": 2800,
        "name": "G5",
        "velocity": 81,
        "duration": 700
      }
    ]
  }
]
